fanfou_sdk/__init__.py
fanfou_sdk/fanfou.py
fanfou_sdk/oauth.py
fanfou_sdk-0.0.3.dist-info/LICENSE
fanfou_sdk-0.0.3.dist-info/METADATA
fanfou_sdk-0.0.3.dist-info/WHEEL
fanfou_sdk-0.0.3.dist-info/top_level.txt
fanfou_sdk-0.0.3.dist-info/RECORD
