Metadata-Version: 2.1
Name: fanfou-sdk
Version: 0.0.3
Summary: Fanfou SDK for Python
Home-page: https://github.com/LitoMore/fanfou-sdk-python
Author: LitoMore
Author-email: litomore@gmail.com
License: MIT
Keywords: fanfou
Platform: any
License-File: LICENSE
Requires-Dist: six
Requires-Dist: requests
